{
    "$schema": "https://schema.management.azure.com/schemas/2019-04-01/deploymentParameters.json#",
    "contentVersion": "1.0.0.0",
    "parameters": {
      "appName": {
        "value": "petcliaca"
      },
      "location": {
        "value": "westeurope"
      },       
      "administratorLogin": {
        "value": "mys_adm"
      },
      "administratorLoginPassword": {
        "value": "IsTrator42!"
      },
      "clientIPAddress": {
        "value": "xxx SET HERE YOUR WORKSTATION IP ADDRESS FOR DEV/TEST"
      },  
      "startIpAddress": {
        "value": "10.42.2.0"
      },
      "endIpAddress": {
        "value": "10.42.3.255"
      }    
    }
  }